MANIFEST.in
README.md
config.json
requirements.txt
setup.cfg
setup.py
iacminer/__init__.py
iacminer/command_line.py
iacminer/filters.py
iacminer/main.py
iacminer/utils.py
iacminer.egg-info/PKG-INFO
iacminer.egg-info/SOURCES.txt
iacminer.egg-info/dependency_links.txt
iacminer.egg-info/entry_points.txt
iacminer.egg-info/top_level.txt
iacminer/entities/__init__.py
iacminer/entities/file.py
iacminer/metrics/__init__.py
iacminer/metrics/metrics.py
iacminer/metrics/text.py
iacminer/miners/__init__.py
iacminer/miners/github.py
iacminer/miners/repository.py
tests/miners/__init__.py
tests/miners/test_github.py
tests/miners/test_repository.py